ldifparse/__init__.py
ldifparse/parse.py
ldifparse/run.py
ldifparse-1.0.1.dist-info/LICENSE
ldifparse-1.0.1.dist-info/METADATA
ldifparse-1.0.1.dist-info/WHEEL
ldifparse-1.0.1.dist-info/entry_points.txt
ldifparse-1.0.1.dist-info/RECORD
