Metadata-Version: 2.1
Name: ldifparse
Version: 1.0.1
Summary: Parse LDIF data into YAML or JSON
Home-page: https://github.com/MatteoBouvier/ldifparse
License: MIT
Author: Matteo Bouvier
Author-email: m.bouvier@vidium-solutions.com
Requires-Python: >=3.10,<4.0
Classifier: License :: OSI Approved :: MIT License
Classifier: Programming Language :: Python :: 3
Classifier: Programming Language :: Python :: 3.10
Classifier: Programming Language :: Python :: 3.11
Classifier: Programming Language :: Python :: 3.12
Requires-Dist: python-ldap (>=3.4.4,<4.0.0)
Requires-Dist: pyyaml (>=6.0.1,<7.0.0)
Requires-Dist: typer (>=0.9.0,<0.10.0)
Project-URL: Repository, https://github.com/MatteoBouvier/ldifparse
